{
  "headlines": [
    {
      "id": "rss_97e6a529b7f5",
      "title": "Defeat from the jaws of victory: Israel reacts to Trump’s Iran ceasefire",
      "summary": "Israel&#039;s confrontation with its regional nemesis leaves Iran both standing and strategically stronger, analysts say.",
      "category": "conflict",
      "countryCode": "US",
      "countryName": "United States",
      "regionName": "United States",
      "locationName": "United States",
      "lat": 38.9167,
      "lng": -77.0666,
      "geoPrecision": "country",
      "geoSource": "keyword",
      "geotagStatus": "resolved",
      "fetchedAt": "2026-04-08T14:19:45.825306+00:00",
      "publishedAt": "2026-04-08T13:34:36+00:00",
      "firstSeenAt": "2026-04-08T14:19:45.825306+00:00",
      "lastUpdatedAt": "2026-04-08T14:19:45.825306+00:00",
      "freshness": "fresh",
      "articleCount": 1,
      "sourceCount": 1,
      "attentionScore": 0.9825,
      "velocityScore": 1.0,
      "crossBorderFactor": 0.95,
      "bubble": true,
      "thumbnailUrl": "",
      "tags": [
        "Defeat",
        "victory:",
        "Israel",
        "reacts",
        "Trump’s",
        "ceasefire"
      ],
      "sources": [
        {
          "name": "aljazeera.com",
          "url": "https://www.aljazeera.com/news/2026/4/8/defeat-from-the-jaws-of-victory-israel-reacts-to-trumps-iran-ceasefire?traffic_source=rss",
          "title": "Defeat from the jaws of victory: Israel reacts to Trump’s Iran ceasefire",
          "publishedAt": "2026-04-08T13:34:36+00:00",
          "thumbnailUrl": ""
        }
      ]
    },
    {
      "id": "rss_5b61060f7935",
      "title": "World Athletics postpones Doha Diamond League amid US-Israel war on Iran",
      "summary": "The multi-discipline event scheduled for May 8 will now be held on June 19 should conditions allow, organisers say.",
      "category": "conflict",
      "countryCode": "IR",
      "countryName": "Iran",
      "regionName": "Iran",
      "locationName": "Iran",
      "lat": 35.5435,
      "lng": 51.7952,
      "geoPrecision": "country",
      "geoSource": "keyword",
      "geotagStatus": "resolved",
      "fetchedAt": "2026-04-08T14:19:45.825444+00:00",
      "publishedAt": "2026-04-08T12:46:23+00:00",
      "firstSeenAt": "2026-04-08T14:19:45.825444+00:00",
      "lastUpdatedAt": "2026-04-08T14:19:45.825444+00:00",
      "freshness": "fresh",
      "articleCount": 1,
      "sourceCount": 1,
      "attentionScore": 0.9825,
      "velocityScore": 1.0,
      "crossBorderFactor": 0.95,
      "bubble": true,
      "thumbnailUrl": "",
      "tags": [
        "World",
        "Athletics",
        "postpones",
        "Diamond",
        "League",
        "US-Israel"
      ],
      "sources": [
        {
          "name": "aljazeera.com",
          "url": "https://www.aljazeera.com/sports/2026/4/8/world-athletics-postpones-doha-diamond-league-amid-us-israel-war-on-iran?traffic_source=rss",
          "title": "World Athletics postpones Doha Diamond League amid US-Israel war on Iran",
          "publishedAt": "2026-04-08T12:46:23+00:00",
          "thumbnailUrl": ""
        }
      ]
    },
    {
      "id": "rss_cfd368f39f11",
      "title": "US-Iran ceasefire will not prompt ‘mass exodus’ of ships through strait of Hormuz, say analysts",
      "summary": "Estimated 2,000 ships, including oil and gas tankers and cruise liners, remain trapped in the Persian Gulf since start of war  There will be no “mass exodus” of ships through the strait of Hormuz, acc…",
      "category": "conflict",
      "countryCode": "IR",
      "countryName": "Iran",
      "regionName": "Iran",
      "locationName": "Iran",
      "lat": 35.8749,
      "lng": 51.3365,
      "geoPrecision": "country",
      "geoSource": "keyword",
      "geotagStatus": "resolved",
      "fetchedAt": "2026-04-08T14:19:47.156236+00:00",
      "publishedAt": "2026-04-08T13:53:55+00:00",
      "firstSeenAt": "2026-04-08T14:19:47.156236+00:00",
      "lastUpdatedAt": "2026-04-08T14:19:47.156236+00:00",
      "freshness": "fresh",
      "articleCount": 1,
      "sourceCount": 1,
      "attentionScore": 0.965,
      "velocityScore": 1.0,
      "crossBorderFactor": 0.9,
      "bubble": true,
      "thumbnailUrl": "",
      "tags": [
        "US-Iran",
        "ceasefire",
        "prompt",
        "‘mass",
        "exodus’",
        "ships"
      ],
      "sources": [
        {
          "name": "theguardian.com",
          "url": "https://www.theguardian.com/world/2026/apr/08/us-iran-ceasefire-mass-exodus-ships-strait-hormuz-analysts",
          "title": "US-Iran ceasefire will not prompt ‘mass exodus’ of ships through strait of Hormuz, say analysts",
          "publishedAt": "2026-04-08T13:53:55+00:00",
          "thumbnailUrl": ""
        }
      ]
    },
    {
      "id": "rss_149ecdc2fcc6",
      "title": "Oil prices plunge 15% to below $100, stocks surge and dollar slumps after Trump announces US-Iran ceasefire – business live",
      "summary": "Oil prices drop most since pandemic while gas prices slide 20%; government bond yields fall sharply as rate hike expectations recede   Despite the sharp drop in crude oil prices today, Mohit Kumar, ch…",
      "category": "conflict",
      "countryCode": "US",
      "countryName": "United States",
      "regionName": "United States",
      "locationName": "United States",
      "lat": 38.9154,
      "lng": -76.9762,
      "geoPrecision": "country",
      "geoSource": "keyword",
      "geotagStatus": "resolved",
      "fetchedAt": "2026-04-08T14:19:47.479478+00:00",
      "publishedAt": "2026-04-08T13:52:06+00:00",
      "firstSeenAt": "2026-04-08T14:19:47.479478+00:00",
      "lastUpdatedAt": "2026-04-08T14:19:47.479478+00:00",
      "freshness": "fresh",
      "articleCount": 1,
      "sourceCount": 1,
      "attentionScore": 0.965,
      "velocityScore": 1.0,
      "crossBorderFactor": 0.9,
      "bubble": true,
      "thumbnailUrl": "",
      "tags": [
        "prices",
        "plunge",
        "below",
        "$100,",
        "stocks",
        "surge"
      ],
      "sources": [
        {
          "name": "theguardian.com",
          "url": "https://www.theguardian.com/business/live/2026/apr/08/oil-prices-drop-stocks-rise-dollar-down-us-iran-ceasefire-business-live",
          "title": "Oil prices plunge 15% to below $100, stocks surge and dollar slumps after Trump announces US-Iran ceasefire – business live",
          "publishedAt": "2026-04-08T13:52:06+00:00",
          "thumbnailUrl": ""
        }
      ]
    },
    {
      "id": "rss_030611ecf8bd",
      "title": "JD Vance warns Iran to act in good faith in 'fragile' ceasefire – video",
      "summary": "Iran must negotiate in 'good faith' during the two-week ceasefire, said the US vice-president, JD Vance, as he called it a 'fragile truce'.  The US and Iran agreed to a two-week conditional ceasefire …",
      "category": "conflict",
      "countryCode": "IR",
      "countryName": "Iran",
      "regionName": "Iran",
      "locationName": "Iran",
      "lat": 35.4515,
      "lng": 51.1892,
      "geoPrecision": "country",
      "geoSource": "keyword",
      "geotagStatus": "resolved",
      "fetchedAt": "2026-04-08T12:43:18.559450+00:00",
      "publishedAt": "2026-04-08T11:48:53+00:00",
      "firstSeenAt": "2026-04-08T12:43:18.559450+00:00",
      "lastUpdatedAt": "2026-04-08T12:43:18.559450+00:00",
      "freshness": "fresh",
      "articleCount": 1,
      "sourceCount": 1,
      "attentionScore": 0.965,
      "velocityScore": 1.0,
      "crossBorderFactor": 0.9,
      "bubble": true,
      "thumbnailUrl": "",
      "tags": [
        "Vance",
        "warns",
        "faith",
        "'fragile'",
        "ceasefire",
        "video"
      ],
      "sources": [
        {
          "name": "theguardian.com",
          "url": "https://www.theguardian.com/us-news/video/2026/apr/08/vance-warns-iran-to-act-in-good-faith-in-fragile-ceasefire-video",
          "title": "JD Vance warns Iran to act in good faith in 'fragile' ceasefire – video",
          "publishedAt": "2026-04-08T11:48:53+00:00",
          "thumbnailUrl": ""
        }
      ]
    },
    {
      "id": "rss_0ee2ebf9c7bc",
      "title": "Britons warned about Russian hackers targeting internet routers for espionage",
      "summary": "Expert stresses importance of staying alert for unusual activity, as hackers could ‘take you to fake sites’     UK politics live – latest updates     Russian hackers are exploiting commonly sold inter…",
      "category": "conflict",
      "countryCode": "RU",
      "countryName": "Russia",
      "regionName": "Russia",
      "locationName": "Russia",
      "lat": 55.6376,
      "lng": 37.5212,
      "geoPrecision": "country",
      "geoSource": "keyword",
      "geotagStatus": "resolved",
      "fetchedAt": "2026-04-08T11:41:02.539520+00:00",
      "publishedAt": "2026-04-08T11:20:45+00:00",
      "firstSeenAt": "2026-04-08T11:41:02.539520+00:00",
      "lastUpdatedAt": "2026-04-08T11:41:02.539520+00:00",
      "freshness": "fresh",
      "articleCount": 1,
      "sourceCount": 1,
      "attentionScore": 0.965,
      "velocityScore": 1.0,
      "crossBorderFactor": 0.9,
      "bubble": true,
      "thumbnailUrl": "",
      "tags": [
        "Britons",
        "warned",
        "about",
        "Russian",
        "hackers",
        "targeting"
      ],
      "sources": [
        {
          "name": "theguardian.com",
          "url": "https://www.theguardian.com/technology/2026/apr/08/britons-warned-russian-hackers-internet-routers-cyber-security-espionage",
          "title": "Britons warned about Russian hackers targeting internet routers for espionage",
          "publishedAt": "2026-04-08T11:20:45+00:00",
          "thumbnailUrl": ""
        }
      ]
    },
    {
      "id": "rss_d1c48c4b9296",
      "title": "REPLAY: Hegseth claims Iran suffered 'devastating military defeat'",
      "summary": "US ⁠Defense ​Secretary ​Pete Hegseth said on ​Wednesday ‌that ⁠the ‌United States ⁠has had a ​decisive military ‌victory over Iran ‌and ​that Tehran's missile program ​has been ​functionally destroyed…",
      "category": "conflict",
      "countryCode": "IR",
      "countryName": "Iran",
      "regionName": "Iran",
      "locationName": "Iran",
      "lat": 35.8423,
      "lng": 51.6885,
      "geoPrecision": "country",
      "geoSource": "keyword",
      "geotagStatus": "resolved",
      "fetchedAt": "2026-04-08T14:19:46.932554+00:00",
      "publishedAt": "2026-04-08T14:01:48+00:00",
      "firstSeenAt": "2026-04-08T14:19:46.932554+00:00",
      "lastUpdatedAt": "2026-04-08T14:19:46.932554+00:00",
      "freshness": "fresh",
      "articleCount": 1,
      "sourceCount": 1,
      "attentionScore": 0.9475,
      "velocityScore": 1.0,
      "crossBorderFactor": 0.85,
      "bubble": true,
      "thumbnailUrl": "",
      "tags": [
        "REPLAY:",
        "Hegseth",
        "claims",
        "suffered",
        "'devastating",
        "military"
      ],
      "sources": [
        {
          "name": "france24.com",
          "url": "https://www.france24.com/en/video/20260408-replay-hegseth-claims-iran-suffered-devastating-military-defeat",
          "title": "REPLAY: Hegseth claims Iran suffered 'devastating military defeat'",
          "publishedAt": "2026-04-08T14:01:48+00:00",
          "thumbnailUrl": ""
        }
      ]
    },
    {
      "id": "rss_db4ad1e90eb1",
      "title": "Oil prices plunge and stocks soar after U.S. and Iran agree on ceasefire",
      "summary": "Investors around the world breathed a sigh of relief at the prospect of peace — and an easing of the global energy crisis.",
      "category": "conflict",
      "countryCode": "IR",
      "countryName": "Iran",
      "regionName": "Iran",
      "locationName": "Iran",
      "lat": 35.6471,
      "lng": 51.705,
      "geoPrecision": "country",
      "geoSource": "keyword",
      "geotagStatus": "resolved",
      "fetchedAt": "2026-04-08T14:19:48.235052+00:00",
      "publishedAt": "2026-04-08T13:33:28+00:00",
      "firstSeenAt": "2026-04-08T14:19:48.235052+00:00",
      "lastUpdatedAt": "2026-04-08T14:19:48.235052+00:00",
      "freshness": "fresh",
      "articleCount": 1,
      "sourceCount": 1,
      "attentionScore": 0.9475,
      "velocityScore": 1.0,
      "crossBorderFactor": 0.85,
      "bubble": true,
      "thumbnailUrl": "",
      "tags": [
        "prices",
        "plunge",
        "stocks",
        "after",
        "agree",
        "ceasefire"
      ],
      "sources": [
        {
          "name": "npr.org",
          "url": "https://www.npr.org/2026/04/08/nx-s1-5776818/wall-street-stocks-oil-trump-iran-ceasefire",
          "title": "Oil prices plunge and stocks soar after U.S. and Iran agree on ceasefire",
          "publishedAt": "2026-04-08T13:33:28+00:00",
          "thumbnailUrl": ""
        }
      ]
    },
    {
      "id": "rss_a329341fb0f9",
      "title": "Ex-NATO general: 'I was worried my former colleagues would become war criminals overnight.'",
      "summary": "A former NATO general tells FRANCE 24 he feared his former colleagues would become war criminals overnight. Michel Yakovleff says US forces are trained to refuse unlawful orders, such as wanton destru…",
      "category": "conflict",
      "countryCode": "US",
      "countryName": "United States",
      "regionName": "United States",
      "locationName": "United States",
      "lat": 38.8624,
      "lng": -77.1074,
      "geoPrecision": "country",
      "geoSource": "keyword",
      "geotagStatus": "resolved",
      "fetchedAt": "2026-04-08T14:19:46.932872+00:00",
      "publishedAt": "2026-04-08T13:25:39+00:00",
      "firstSeenAt": "2026-04-08T14:19:46.932872+00:00",
      "lastUpdatedAt": "2026-04-08T14:19:46.932872+00:00",
      "freshness": "fresh",
      "articleCount": 1,
      "sourceCount": 1,
      "attentionScore": 0.9475,
      "velocityScore": 1.0,
      "crossBorderFactor": 0.85,
      "bubble": true,
      "thumbnailUrl": "",
      "tags": [
        "Ex-NATO",
        "general:",
        "worried",
        "former",
        "colleagues",
        "would"
      ],
      "sources": [
        {
          "name": "france24.com",
          "url": "https://www.france24.com/en/tv-shows/perspective/20260408-i-was-worried-my-former-colleagues-were-going-to-become-war-criminals-overnight-yak-i-was-worried-my-former-colleagues-were-going-to-become-war-criminals-overnight-yakovleffovleff",
          "title": "Ex-NATO general: 'I was worried my former colleagues would become war criminals overnight.'",
          "publishedAt": "2026-04-08T13:25:39+00:00",
          "thumbnailUrl": ""
        }
      ]
    },
    {
      "id": "rss_a728ef6be631",
      "title": "US war on Iran: Lucas makes case for 'discussions & dialogue over renewing violence & confrontation'",
      "summary": "Genie Godula is pleased to welcome Scott Lucas, Professor of American Studies and Int'l Politics at the Clinton Institute, University College Dublin. According to Professor Lucas, this is not a moment…",
      "category": "conflict",
      "countryCode": "US",
      "countryName": "United States",
      "regionName": "United States",
      "locationName": "United States",
      "lat": 38.9825,
      "lng": -77.2287,
      "geoPrecision": "country",
      "geoSource": "keyword",
      "geotagStatus": "resolved",
      "fetchedAt": "2026-04-08T14:19:46.932994+00:00",
      "publishedAt": "2026-04-08T13:07:00+00:00",
      "firstSeenAt": "2026-04-08T14:19:46.932994+00:00",
      "lastUpdatedAt": "2026-04-08T14:19:46.932994+00:00",
      "freshness": "fresh",
      "articleCount": 1,
      "sourceCount": 1,
      "attentionScore": 0.9475,
      "velocityScore": 1.0,
      "crossBorderFactor": 0.85,
      "bubble": true,
      "thumbnailUrl": "",
      "tags": [
        "Iran:",
        "Lucas",
        "makes",
        "'discussions",
        "dialogue",
        "renewing"
      ],
      "sources": [
        {
          "name": "france24.com",
          "url": "https://www.france24.com/en/video/20260408-us-war-on-iran-lucas-makes-case-for-discussions-dialogue-over-renewing-violence-confrontation-1",
          "title": "US war on Iran: Lucas makes case for 'discussions & dialogue over renewing violence & confrontation'",
          "publishedAt": "2026-04-08T13:07:00+00:00",
          "thumbnailUrl": ""
        }
      ]
    }
  ],
  "generatedAt": "2026-04-08T14:19:51.646176+00:00"
}