{
  "headlines": [
    {
      "id": "rss_c7d74b79bdc2",
      "title": "Cannes juror denounces Hollywood boycott of actors for Gaza war views",
      "summary": "2026 Cannes Film Festival juror Paul Laverty denounced Hollywood for boycotting actors who’ve opposed the Gaza war.",
      "category": "conflict",
      "countryCode": "IL",
      "countryName": "Israel",
      "regionName": "Israel",
      "locationName": "Israel",
      "lat": 31.4879,
      "lng": 34.4964,
      "geoPrecision": "country",
      "geoSource": "keyword",
      "geotagStatus": "resolved",
      "fetchedAt": "2026-05-12T21:41:04.934950+00:00",
      "publishedAt": "2026-05-12T20:55:57+00:00",
      "firstSeenAt": "2026-05-12T21:41:04.934950+00:00",
      "lastUpdatedAt": "2026-05-12T21:41:04.934950+00:00",
      "freshness": "fresh",
      "articleCount": 1,
      "sourceCount": 1,
      "attentionScore": 0.9825,
      "velocityScore": 1.0,
      "crossBorderFactor": 0.95,
      "bubble": true,
      "thumbnailUrl": "",
      "tags": [
        "Cannes",
        "juror",
        "denounces",
        "Hollywood",
        "boycott",
        "actors"
      ],
      "sources": [
        {
          "name": "aljazeera.com",
          "url": "https://www.aljazeera.com/video/newsfeed/2026/5/12/cannes-juror-denounces-hollywood-boycott-of-actors-for-gaza-war-views?traffic_source=rss",
          "title": "Cannes juror denounces Hollywood boycott of actors for Gaza war views",
          "publishedAt": "2026-05-12T20:55:57+00:00",
          "thumbnailUrl": ""
        }
      ]
    },
    {
      "id": "rss_00758a9147f0",
      "title": "Trump downplays US-Iran differences as he heads to Beijing to meet with Xi",
      "summary": "Trump gives conflicting messages on prominence of Iran war in upcoming talks, with his administration emphasising trade.",
      "category": "politics",
      "countryCode": "CN",
      "countryName": "China",
      "regionName": "China",
      "locationName": "China",
      "lat": 39.8042,
      "lng": 116.5198,
      "geoPrecision": "country",
      "geoSource": "keyword",
      "geotagStatus": "resolved",
      "fetchedAt": "2026-05-12T21:41:04.934703+00:00",
      "publishedAt": "2026-05-12T21:02:19+00:00",
      "firstSeenAt": "2026-05-12T21:41:04.934703+00:00",
      "lastUpdatedAt": "2026-05-12T21:41:04.934703+00:00",
      "freshness": "fresh",
      "articleCount": 1,
      "sourceCount": 1,
      "attentionScore": 0.9425,
      "velocityScore": 1.0,
      "crossBorderFactor": 0.95,
      "bubble": true,
      "thumbnailUrl": "",
      "tags": [
        "Trump",
        "downplays",
        "US-Iran",
        "differences",
        "heads",
        "Beijing"
      ],
      "sources": [
        {
          "name": "aljazeera.com",
          "url": "https://www.aljazeera.com/news/2026/5/12/trump-downplays-us-iran-differences-as-he-heads-to-beijing-to-meet-with-xi?traffic_source=rss",
          "title": "Trump downplays US-Iran differences as he heads to Beijing to meet with Xi",
          "publishedAt": "2026-05-12T21:02:19+00:00",
          "thumbnailUrl": ""
        }
      ]
    },
    {
      "id": "rss_0db8f2d72d0d",
      "title": "Trump backs Pakistan as Iran mediator after criticism from Lindsey Graham",
      "summary": "US president lauds Islamabad, but his Republican ally says he does not trust Pakistan to facilitate Iran diplomacy.",
      "category": "politics",
      "countryCode": "PK",
      "countryName": "Pakistan",
      "regionName": "Pakistan",
      "locationName": "Pakistan",
      "lat": 33.6737,
      "lng": 73.1902,
      "geoPrecision": "country",
      "geoSource": "keyword",
      "geotagStatus": "resolved",
      "fetchedAt": "2026-05-12T21:41:04.935020+00:00",
      "publishedAt": "2026-05-12T20:24:30+00:00",
      "firstSeenAt": "2026-05-12T21:41:04.935020+00:00",
      "lastUpdatedAt": "2026-05-12T21:41:04.935020+00:00",
      "freshness": "fresh",
      "articleCount": 1,
      "sourceCount": 1,
      "attentionScore": 0.9425,
      "velocityScore": 1.0,
      "crossBorderFactor": 0.95,
      "bubble": true,
      "thumbnailUrl": "",
      "tags": [
        "Trump",
        "backs",
        "Pakistan",
        "mediator",
        "after",
        "criticism"
      ],
      "sources": [
        {
          "name": "aljazeera.com",
          "url": "https://www.aljazeera.com/news/2026/5/12/trump-backs-pakistan-as-iran-mediator-after-criticism-from-lindsey-graham?traffic_source=rss",
          "title": "Trump backs Pakistan as Iran mediator after criticism from Lindsey Graham",
          "publishedAt": "2026-05-12T20:24:30+00:00",
          "thumbnailUrl": ""
        }
      ]
    },
    {
      "id": "rss_1dbf60e2cce0",
      "title": "Why have peace efforts failed to end conflict in Sudan?",
      "summary": "The UN says the use of drones is making the conflict more dangerous.",
      "category": "politics",
      "countryCode": "SD",
      "countryName": "Sudan",
      "regionName": "Sudan",
      "locationName": "Sudan",
      "lat": 15.5156,
      "lng": 32.3432,
      "geoPrecision": "country",
      "geoSource": "keyword",
      "geotagStatus": "resolved",
      "fetchedAt": "2026-05-12T21:41:04.935103+00:00",
      "publishedAt": "2026-05-12T19:54:05+00:00",
      "firstSeenAt": "2026-05-12T21:41:04.935103+00:00",
      "lastUpdatedAt": "2026-05-12T21:41:04.935103+00:00",
      "freshness": "fresh",
      "articleCount": 1,
      "sourceCount": 1,
      "attentionScore": 0.9425,
      "velocityScore": 1.0,
      "crossBorderFactor": 0.95,
      "bubble": true,
      "thumbnailUrl": "",
      "tags": [
        "peace",
        "efforts",
        "failed",
        "conflict",
        "Sudan?"
      ],
      "sources": [
        {
          "name": "aljazeera.com",
          "url": "https://www.aljazeera.com/video/inside-story/2026/5/12/why-have-peace-efforts-failed-to-end-conflict-in-sudan?traffic_source=rss",
          "title": "Why have peace efforts failed to end conflict in Sudan?",
          "publishedAt": "2026-05-12T19:54:05+00:00",
          "thumbnailUrl": ""
        }
      ]
    },
    {
      "id": "rss_ba9d35216d3c",
      "title": "Red Cross says people displaced by conflict in Colombia doubled last year",
      "summary": "Annual report by ICRC finds worsening conditions for Colombian civilians amid continued fighting between armed groups.",
      "category": "politics",
      "countryCode": "CO",
      "countryName": "Colombia",
      "regionName": "Colombia",
      "locationName": "Colombia",
      "lat": 4.5702,
      "lng": -74.2314,
      "geoPrecision": "country",
      "geoSource": "keyword",
      "geotagStatus": "resolved",
      "fetchedAt": "2026-05-12T21:41:04.935187+00:00",
      "publishedAt": "2026-05-12T19:52:10+00:00",
      "firstSeenAt": "2026-05-12T21:41:04.935187+00:00",
      "lastUpdatedAt": "2026-05-12T21:41:04.935187+00:00",
      "freshness": "fresh",
      "articleCount": 1,
      "sourceCount": 1,
      "attentionScore": 0.9425,
      "velocityScore": 1.0,
      "crossBorderFactor": 0.95,
      "bubble": true,
      "thumbnailUrl": "",
      "tags": [
        "Cross",
        "people",
        "displaced",
        "conflict",
        "Colombia",
        "doubled"
      ],
      "sources": [
        {
          "name": "aljazeera.com",
          "url": "https://www.aljazeera.com/news/2026/5/12/red-cross-says-people-displaced-by-conflict-in-colombia-doubled-last-year?traffic_source=rss",
          "title": "Red Cross says people displaced by conflict in Colombia doubled last year",
          "publishedAt": "2026-05-12T19:52:10+00:00",
          "thumbnailUrl": ""
        }
      ]
    },
    {
      "id": "rss_ad54e04a90f9",
      "title": "Iran war boosts Beijing ahead of Trump visit, experts say",
      "summary": "As US President Donald Trump prepares to meet his Chinese counterpart in Beijing, some analysts say the war in Iran has significantly shifted the power dynamics in China's favour.",
      "category": "conflict",
      "countryCode": "CN",
      "countryName": "China",
      "regionName": "China",
      "locationName": "China",
      "lat": 39.8891,
      "lng": 116.6666,
      "geoPrecision": "country",
      "geoSource": "keyword",
      "geotagStatus": "resolved",
      "fetchedAt": "2026-05-12T22:45:41.787699+00:00",
      "publishedAt": "2026-05-12T22:33:23+00:00",
      "firstSeenAt": "2026-05-12T22:45:41.787699+00:00",
      "lastUpdatedAt": "2026-05-12T22:45:41.787699+00:00",
      "freshness": "fresh",
      "articleCount": 1,
      "sourceCount": 1,
      "attentionScore": 0.93,
      "velocityScore": 1.0,
      "crossBorderFactor": 0.8,
      "bubble": true,
      "thumbnailUrl": "",
      "tags": [
        "boosts",
        "Beijing",
        "ahead",
        "Trump",
        "visit,",
        "experts"
      ],
      "sources": [
        {
          "name": "abc.net.au",
          "url": "https://www.abc.net.au/news/2026-05-13/donald-trump-visits-china-for-summit-with-xi-jinping/106673264",
          "title": "Iran war boosts Beijing ahead of Trump visit, experts say",
          "publishedAt": "2026-05-12T22:33:23+00:00",
          "thumbnailUrl": ""
        }
      ]
    },
    {
      "id": "rss_3da3429ae51d",
      "title": "Death of man struck by Frontier Airlines plane ruled suicide by medical examiner",
      "summary": "Michael Mott, 41, jumped the fence at Denver international airport and had reached the runway when he was struck  The man who was fatally struck on Friday by a departing Frontier Airlines flight on th…",
      "category": "politics",
      "countryCode": "US",
      "countryName": "United States",
      "regionName": "United States",
      "locationName": "United States",
      "lat": 38.8042,
      "lng": -77.321,
      "geoPrecision": "country",
      "geoSource": "keyword",
      "geotagStatus": "resolved",
      "fetchedAt": "2026-05-12T22:45:39.862830+00:00",
      "publishedAt": "2026-05-12T22:04:03+00:00",
      "firstSeenAt": "2026-05-12T22:45:39.862830+00:00",
      "lastUpdatedAt": "2026-05-12T22:45:39.862830+00:00",
      "freshness": "fresh",
      "articleCount": 1,
      "sourceCount": 1,
      "attentionScore": 0.925,
      "velocityScore": 1.0,
      "crossBorderFactor": 0.9,
      "bubble": true,
      "thumbnailUrl": "",
      "tags": [
        "Death",
        "struck",
        "Frontier",
        "Airlines",
        "plane",
        "ruled"
      ],
      "sources": [
        {
          "name": "theguardian.com",
          "url": "https://www.theguardian.com/us-news/2026/may/12/frontier-airlines-plane-suicide",
          "title": "Death of man struck by Frontier Airlines plane ruled suicide by medical examiner",
          "publishedAt": "2026-05-12T22:04:03+00:00",
          "thumbnailUrl": ""
        }
      ]
    },
    {
      "id": "rss_8fdeb2ec4716",
      "title": "Capacity of lifts not kept up with UK obesity levels, study shows",
      "summary": "Research on weight limits of elevators made in UK and Europe 1972-2004 raises concerns over safety and equity  Lifts are no longer big enough to fit the UK’s larger citizens, according to researchers.…",
      "category": "politics",
      "countryCode": "GB",
      "countryName": "United Kingdom",
      "regionName": "United Kingdom",
      "locationName": "United Kingdom",
      "lat": 51.6247,
      "lng": -0.4589,
      "geoPrecision": "country",
      "geoSource": "keyword",
      "geotagStatus": "resolved",
      "fetchedAt": "2026-05-12T22:45:39.862508+00:00",
      "publishedAt": "2026-05-12T22:01:11+00:00",
      "firstSeenAt": "2026-05-12T22:45:39.862508+00:00",
      "lastUpdatedAt": "2026-05-12T22:45:39.862508+00:00",
      "freshness": "fresh",
      "articleCount": 1,
      "sourceCount": 1,
      "attentionScore": 0.925,
      "velocityScore": 1.0,
      "crossBorderFactor": 0.9,
      "bubble": true,
      "thumbnailUrl": "",
      "tags": [
        "Capacity",
        "lifts",
        "obesity",
        "levels,",
        "study",
        "shows"
      ],
      "sources": [
        {
          "name": "theguardian.com",
          "url": "https://www.theguardian.com/society/2026/may/12/capacity-lifts-elevators-weight-limits-obesity-safety-equity",
          "title": "Capacity of lifts not kept up with UK obesity levels, study shows",
          "publishedAt": "2026-05-12T22:01:11+00:00",
          "thumbnailUrl": ""
        }
      ]
    },
    {
      "id": "rss_ba7f8d76e48d",
      "title": "New York hospital system receives subpoena over trans youth healthcare",
      "summary": "Request is one of the justice department’s latest attempts to track and regulate gender-affirming care for minors     Sign up for the Breaking News US newsletter email        A  Texas  federal prosecu…",
      "category": "politics",
      "countryCode": "US",
      "countryName": "United States",
      "regionName": "United States",
      "locationName": "United States",
      "lat": 40.9458,
      "lng": -74.1511,
      "geoPrecision": "country",
      "geoSource": "keyword",
      "geotagStatus": "resolved",
      "fetchedAt": "2026-05-12T22:45:39.983900+00:00",
      "publishedAt": "2026-05-12T21:52:01+00:00",
      "firstSeenAt": "2026-05-12T22:45:39.983900+00:00",
      "lastUpdatedAt": "2026-05-12T22:45:39.983900+00:00",
      "freshness": "fresh",
      "articleCount": 1,
      "sourceCount": 1,
      "attentionScore": 0.925,
      "velocityScore": 1.0,
      "crossBorderFactor": 0.9,
      "bubble": true,
      "thumbnailUrl": "",
      "tags": [
        "hospital",
        "system",
        "receives",
        "subpoena",
        "trans",
        "youth"
      ],
      "sources": [
        {
          "name": "theguardian.com",
          "url": "https://www.theguardian.com/us-news/2026/may/12/new-york-hospital-langone-transgender-care",
          "title": "New York hospital system receives subpoena over trans youth healthcare",
          "publishedAt": "2026-05-12T21:52:01+00:00",
          "thumbnailUrl": ""
        }
      ]
    },
    {
      "id": "rss_f7b3d6d143a6",
      "title": "South Carolina Republicans defy Trump’s demands for redistricting",
      "summary": "Republican leader acknowledges ‘likely consequences’ for resisting US president’s demands to redraw map     Sign up for the Breaking News US newsletter email      South Carolina  state senators on Tue…",
      "category": "politics",
      "countryCode": "US",
      "countryName": "United States",
      "regionName": "United States",
      "locationName": "United States",
      "lat": 38.5246,
      "lng": -76.6966,
      "geoPrecision": "country",
      "geoSource": "keyword",
      "geotagStatus": "resolved",
      "fetchedAt": "2026-05-12T22:45:39.862933+00:00",
      "publishedAt": "2026-05-12T21:46:08+00:00",
      "firstSeenAt": "2026-05-12T22:45:39.862933+00:00",
      "lastUpdatedAt": "2026-05-12T22:45:39.862933+00:00",
      "freshness": "fresh",
      "articleCount": 1,
      "sourceCount": 1,
      "attentionScore": 0.925,
      "velocityScore": 1.0,
      "crossBorderFactor": 0.9,
      "bubble": true,
      "thumbnailUrl": "",
      "tags": [
        "South",
        "Carolina",
        "Republicans",
        "Trump’s",
        "demands",
        "redistricting"
      ],
      "sources": [
        {
          "name": "theguardian.com",
          "url": "https://www.theguardian.com/us-news/2026/may/12/south-carolina-republicans-defy-trump-redistricting",
          "title": "South Carolina Republicans defy Trump’s demands for redistricting",
          "publishedAt": "2026-05-12T21:46:08+00:00",
          "thumbnailUrl": ""
        }
      ]
    }
  ],
  "generatedAt": "2026-05-12T22:45:42.982507+00:00"
}