{
  "headlines": [
    {
      "id": "rss_79220754fbab",
      "title": "Four killed in Ukraine a day after deadliest Russian attacks this year",
      "summary": "At least five people were separately killed in Ukrainian attacks on Russia&#039;s border regions.",
      "category": "conflict",
      "countryCode": "UA",
      "countryName": "Ukraine",
      "regionName": "Ukraine",
      "locationName": "Ukraine",
      "lat": 50.433,
      "lng": 30.5988,
      "geoPrecision": "country",
      "geoSource": "keyword",
      "geotagStatus": "resolved",
      "fetchedAt": "2026-07-03T10:17:33.685756+00:00",
      "publishedAt": "2026-07-03T09:26:27+00:00",
      "firstSeenAt": "2026-07-03T10:17:33.685756+00:00",
      "lastUpdatedAt": "2026-07-03T10:17:33.685756+00:00",
      "freshness": "fresh",
      "articleCount": 1,
      "sourceCount": 1,
      "attentionScore": 0.9825,
      "velocityScore": 1.0,
      "crossBorderFactor": 0.95,
      "bubble": true,
      "thumbnailUrl": "",
      "tags": [
        "killed",
        "Ukraine",
        "after",
        "deadliest",
        "Russian",
        "attacks"
      ],
      "sources": [
        {
          "name": "aljazeera.com",
          "url": "https://www.aljazeera.com/news/2026/7/3/four-killed-in-ukraine-a-day-after-deadliest-russian-attacks-this-year?traffic_source=rss",
          "title": "Four killed in Ukraine a day after deadliest Russian attacks this year",
          "publishedAt": "2026-07-03T09:26:27+00:00",
          "thumbnailUrl": ""
        }
      ]
    },
    {
      "id": "rss_a993eb7c4ebe",
      "title": "EU lawmaker investigating surveillance hacked by Israeli spyware, report says",
      "summary": "Greek former parliamentarian Stelios Kouloglou targeted with Pegasus software, Citizen Lab analysis finds.",
      "category": "conflict",
      "countryCode": "IL",
      "countryName": "Israel",
      "regionName": "Israel",
      "locationName": "Israel",
      "lat": 31.6487,
      "lng": 35.2578,
      "geoPrecision": "country",
      "geoSource": "keyword",
      "geotagStatus": "resolved",
      "fetchedAt": "2026-07-03T10:17:33.686088+00:00",
      "publishedAt": "2026-07-03T08:20:51+00:00",
      "firstSeenAt": "2026-07-03T10:17:33.686088+00:00",
      "lastUpdatedAt": "2026-07-03T10:17:33.686088+00:00",
      "freshness": "fresh",
      "articleCount": 1,
      "sourceCount": 1,
      "attentionScore": 0.9825,
      "velocityScore": 1.0,
      "crossBorderFactor": 0.95,
      "bubble": true,
      "thumbnailUrl": "",
      "tags": [
        "lawmaker",
        "investigating",
        "surveillance",
        "hacked",
        "Israeli",
        "spyware,"
      ],
      "sources": [
        {
          "name": "aljazeera.com",
          "url": "https://www.aljazeera.com/economy/2026/7/3/eu-lawmaker-investigating-surveillance-hacked-by-israeli-spyware-report-says?traffic_source=rss",
          "title": "EU lawmaker investigating surveillance hacked by Israeli spyware, report says",
          "publishedAt": "2026-07-03T08:20:51+00:00",
          "thumbnailUrl": ""
        }
      ]
    },
    {
      "id": "rss_923cc68cc2ef",
      "title": "At least 40 killed in passenger bus crash in southwest Pakistan",
      "summary": "Bus loses control and falls into rocky ravine near border of Balochistan and Khyber Pakhtunkhwa, officials say.",
      "category": "conflict",
      "countryCode": "PK",
      "countryName": "Pakistan",
      "regionName": "Pakistan",
      "locationName": "Pakistan",
      "lat": 33.927,
      "lng": 73.3457,
      "geoPrecision": "country",
      "geoSource": "keyword",
      "geotagStatus": "resolved",
      "fetchedAt": "2026-07-03T10:17:33.686560+00:00",
      "publishedAt": "2026-07-03T07:24:42+00:00",
      "firstSeenAt": "2026-07-03T10:17:33.686560+00:00",
      "lastUpdatedAt": "2026-07-03T10:17:33.686560+00:00",
      "freshness": "fresh",
      "articleCount": 1,
      "sourceCount": 1,
      "attentionScore": 0.9825,
      "velocityScore": 1.0,
      "crossBorderFactor": 0.95,
      "bubble": true,
      "thumbnailUrl": "",
      "tags": [
        "least",
        "killed",
        "passenger",
        "crash",
        "southwest",
        "Pakistan"
      ],
      "sources": [
        {
          "name": "aljazeera.com",
          "url": "https://www.aljazeera.com/news/2026/7/3/at-least-40-killed-in-passenger-bus-crash-in-southwest-pakistan?traffic_source=rss",
          "title": "At least 40 killed in passenger bus crash in southwest Pakistan",
          "publishedAt": "2026-07-03T07:24:42+00:00",
          "thumbnailUrl": ""
        }
      ]
    },
    {
      "id": "rss_fe27ddea5f68",
      "title": "Woman suspected in Monaco parcel bombing reportedly seen in Germany",
      "summary": "Suspect is said to have tried to pass as a man during attack apparently targeting Ukrainian-born oligarch  The main suspect in ⁠a ⁠ bomb attack in ​Monaco  ⁠this week is a woman ⁠who ​has ‌been spotte…",
      "category": "conflict",
      "countryCode": "DE",
      "countryName": "Germany",
      "regionName": "Germany",
      "locationName": "Germany",
      "lat": 52.9521,
      "lng": 13.5197,
      "geoPrecision": "country",
      "geoSource": "keyword",
      "geotagStatus": "resolved",
      "fetchedAt": "2026-07-03T10:17:34.715091+00:00",
      "publishedAt": "2026-07-03T09:05:33+00:00",
      "firstSeenAt": "2026-07-03T10:17:34.715091+00:00",
      "lastUpdatedAt": "2026-07-03T10:17:34.715091+00:00",
      "freshness": "fresh",
      "articleCount": 1,
      "sourceCount": 1,
      "attentionScore": 0.965,
      "velocityScore": 1.0,
      "crossBorderFactor": 0.9,
      "bubble": true,
      "thumbnailUrl": "",
      "tags": [
        "Woman",
        "suspected",
        "Monaco",
        "parcel",
        "bombing",
        "reportedly"
      ],
      "sources": [
        {
          "name": "theguardian.com",
          "url": "https://www.theguardian.com/world/2026/jul/03/suspect-identified-in-monaco-parcel-bombing-that-wounded-sanctioned-ukrainian-born-oligarch",
          "title": "Woman suspected in Monaco parcel bombing reportedly seen in Germany",
          "publishedAt": "2026-07-03T09:05:33+00:00",
          "thumbnailUrl": ""
        }
      ]
    },
    {
      "id": "rss_d6f206e5c80f",
      "title": "Kyiv mourns 30 killed in Russian attack as rescuers continue search",
      "summary": "Rescuers continued ⁠clearing the rubble ​in Kyiv on Friday in the hope of finding more survivors, as flags were ​lowered to half mast to mark a day of mourning, a day after a Russian missile and drone…",
      "category": "conflict",
      "countryCode": "UA",
      "countryName": "Ukraine",
      "regionName": "Ukraine",
      "locationName": "Ukraine",
      "lat": 50.2379,
      "lng": 30.7399,
      "geoPrecision": "country",
      "geoSource": "keyword",
      "geotagStatus": "resolved",
      "fetchedAt": "2026-07-03T10:17:34.533965+00:00",
      "publishedAt": "2026-07-03T09:15:01+00:00",
      "firstSeenAt": "2026-07-03T10:17:34.533965+00:00",
      "lastUpdatedAt": "2026-07-03T10:17:34.533965+00:00",
      "freshness": "fresh",
      "articleCount": 1,
      "sourceCount": 1,
      "attentionScore": 0.9475,
      "velocityScore": 1.0,
      "crossBorderFactor": 0.85,
      "bubble": true,
      "thumbnailUrl": "",
      "tags": [
        "mourns",
        "killed",
        "Russian",
        "attack",
        "rescuers",
        "continue"
      ],
      "sources": [
        {
          "name": "france24.com",
          "url": "https://www.france24.com/en/video/20260703-kyiv-mourns-30-killed-in-russian-attack-as-rescuers-continue-search",
          "title": "Kyiv mourns 30 killed in Russian attack as rescuers continue search",
          "publishedAt": "2026-07-03T09:15:01+00:00",
          "thumbnailUrl": ""
        }
      ]
    },
    {
      "id": "rss_650af84a9e1e",
      "title": "How a fertilizer shortage caused by the Iran war could affect U.S. food prices",
      "summary": "The closure of the Strait of Hormuz disrupted shipments of fertilizer and natural gas, a key component in fertilizer manufacturing. It's unlikely to cause major price hikes for U.S. grocery shoppers.",
      "category": "conflict",
      "countryCode": "IR",
      "countryName": "Iran",
      "regionName": "Iran",
      "locationName": "Iran",
      "lat": 35.682,
      "lng": 51.454,
      "geoPrecision": "country",
      "geoSource": "keyword",
      "geotagStatus": "resolved",
      "fetchedAt": "2026-07-03T10:17:36.525966+00:00",
      "publishedAt": "2026-07-03T09:00:00+00:00",
      "firstSeenAt": "2026-07-03T10:17:36.525966+00:00",
      "lastUpdatedAt": "2026-07-03T10:17:36.525966+00:00",
      "freshness": "fresh",
      "articleCount": 1,
      "sourceCount": 1,
      "attentionScore": 0.9475,
      "velocityScore": 1.0,
      "crossBorderFactor": 0.85,
      "bubble": true,
      "thumbnailUrl": "",
      "tags": [
        "fertilizer",
        "shortage",
        "caused",
        "could",
        "affect",
        "prices"
      ],
      "sources": [
        {
          "name": "npr.org",
          "url": "https://www.npr.org/2026/07/03/nx-s1-5877344/fertilizer-shortage-food-prices",
          "title": "How a fertilizer shortage caused by the Iran war could affect U.S. food prices",
          "publishedAt": "2026-07-03T09:00:00+00:00",
          "thumbnailUrl": ""
        }
      ]
    },
    {
      "id": "rss_d1a9083ea15d",
      "title": "US Police staff spark altercation with Egyptian players posing with fans",
      "summary": "US Police sparked a confrontation with Egypt&#039;s national team as they posed with fans at their hotel in Dallas.",
      "category": "politics",
      "countryCode": "EG",
      "countryName": "Egypt",
      "regionName": "Egypt",
      "locationName": "Egypt",
      "lat": 30.1341,
      "lng": 31.3692,
      "geoPrecision": "country",
      "geoSource": "keyword",
      "geotagStatus": "resolved",
      "fetchedAt": "2026-07-03T10:17:33.685569+00:00",
      "publishedAt": "2026-07-03T10:13:07+00:00",
      "firstSeenAt": "2026-07-03T10:17:33.685569+00:00",
      "lastUpdatedAt": "2026-07-03T10:17:33.685569+00:00",
      "freshness": "fresh",
      "articleCount": 1,
      "sourceCount": 1,
      "attentionScore": 0.9425,
      "velocityScore": 1.0,
      "crossBorderFactor": 0.95,
      "bubble": true,
      "thumbnailUrl": "",
      "tags": [
        "Police",
        "staff",
        "spark",
        "altercation",
        "Egyptian",
        "players"
      ],
      "sources": [
        {
          "name": "aljazeera.com",
          "url": "https://www.aljazeera.com/video/newsfeed/2026/7/3/us-police-staff-spark-altercation-with-egyptian-players-posing-with-fans?traffic_source=rss",
          "title": "US Police staff spark altercation with Egyptian players posing with fans",
          "publishedAt": "2026-07-03T10:13:07+00:00",
          "thumbnailUrl": ""
        }
      ]
    },
    {
      "id": "rss_6ca3ba6a1e0c",
      "title": "Israel approves plan to establish 13 new settlements in occupied West Bank",
      "summary": "Palestinian officials warn against the implications of the plan, saying it would further isolate East Jerusalem.",
      "category": "politics",
      "countryCode": "IL",
      "countryName": "Israel",
      "regionName": "Israel",
      "locationName": "Israel",
      "lat": 31.509,
      "lng": 35.384,
      "geoPrecision": "country",
      "geoSource": "keyword",
      "geotagStatus": "resolved",
      "fetchedAt": "2026-07-03T10:17:33.685682+00:00",
      "publishedAt": "2026-07-03T09:59:35+00:00",
      "firstSeenAt": "2026-07-03T10:17:33.685682+00:00",
      "lastUpdatedAt": "2026-07-03T10:17:33.685682+00:00",
      "freshness": "fresh",
      "articleCount": 1,
      "sourceCount": 1,
      "attentionScore": 0.9425,
      "velocityScore": 1.0,
      "crossBorderFactor": 0.95,
      "bubble": true,
      "thumbnailUrl": "",
      "tags": [
        "Israel",
        "approves",
        "establish",
        "settlements",
        "occupied"
      ],
      "sources": [
        {
          "name": "aljazeera.com",
          "url": "https://www.aljazeera.com/news/2026/7/3/israel-approves-plan-to-establish-13-new-settlements-in-occupied-west-bank?traffic_source=rss",
          "title": "Israel approves plan to establish 13 new settlements in occupied West Bank",
          "publishedAt": "2026-07-03T09:59:35+00:00",
          "thumbnailUrl": ""
        }
      ]
    },
    {
      "id": "rss_2e090c9a524e",
      "title": "$500m for Trump, access for Pakistan: How a crypto-diplomatic bet paid off",
      "summary": "The crypto firm that brought Trump a windfall has also allowed Pakistan to gain clout with US administration.",
      "category": "politics",
      "countryCode": "US",
      "countryName": "United States",
      "regionName": "United States",
      "locationName": "United States",
      "lat": 38.9342,
      "lng": -77.2774,
      "geoPrecision": "country",
      "geoSource": "keyword",
      "geotagStatus": "resolved",
      "fetchedAt": "2026-07-03T10:17:33.686016+00:00",
      "publishedAt": "2026-07-03T08:41:32+00:00",
      "firstSeenAt": "2026-07-03T10:17:33.686016+00:00",
      "lastUpdatedAt": "2026-07-03T10:17:33.686016+00:00",
      "freshness": "fresh",
      "articleCount": 1,
      "sourceCount": 1,
      "attentionScore": 0.9425,
      "velocityScore": 1.0,
      "crossBorderFactor": 0.95,
      "bubble": true,
      "thumbnailUrl": "",
      "tags": [
        "$500m",
        "Trump,",
        "access",
        "Pakistan:",
        "crypto-diplomatic"
      ],
      "sources": [
        {
          "name": "aljazeera.com",
          "url": "https://www.aljazeera.com/news/2026/7/3/500m-for-trump-access-for-pakistan-how-a-crypto-diplomatic-bet-paid-off?traffic_source=rss",
          "title": "$500m for Trump, access for Pakistan: How a crypto-diplomatic bet paid off",
          "publishedAt": "2026-07-03T08:41:32+00:00",
          "thumbnailUrl": ""
        }
      ]
    },
    {
      "id": "rss_ba3d765a1e20",
      "title": "Iran’s Khamenei funeral: Which world leaders are attending?",
      "summary": "Several heads of state and other government officials will gather in Tehran for Khamenei&#039;s state funeral.",
      "category": "politics",
      "countryCode": "IR",
      "countryName": "Iran",
      "regionName": "Iran",
      "locationName": "Iran",
      "lat": 35.8681,
      "lng": 51.0595,
      "geoPrecision": "country",
      "geoSource": "keyword",
      "geotagStatus": "resolved",
      "fetchedAt": "2026-07-03T10:17:33.686253+00:00",
      "publishedAt": "2026-07-03T08:04:08+00:00",
      "firstSeenAt": "2026-07-03T10:17:33.686253+00:00",
      "lastUpdatedAt": "2026-07-03T10:17:33.686253+00:00",
      "freshness": "fresh",
      "articleCount": 1,
      "sourceCount": 1,
      "attentionScore": 0.9425,
      "velocityScore": 1.0,
      "crossBorderFactor": 0.95,
      "bubble": true,
      "thumbnailUrl": "",
      "tags": [
        "Iran’s",
        "Khamenei",
        "funeral:",
        "Which",
        "world",
        "leaders"
      ],
      "sources": [
        {
          "name": "aljazeera.com",
          "url": "https://www.aljazeera.com/news/2026/7/3/irans-khamenei-funeral-which-world-leaders-are-attending?traffic_source=rss",
          "title": "Iran’s Khamenei funeral: Which world leaders are attending?",
          "publishedAt": "2026-07-03T08:04:08+00:00",
          "thumbnailUrl": ""
        }
      ]
    }
  ],
  "generatedAt": "2026-07-03T10:17:44.540540+00:00"
}