{
  "generatedAt": "2026-04-26T08:05:14.520184+00:00",
  "timeRange": "24h",
  "risingEvents": [
    {
      "id": "rss_e1d8f7601e1d",
      "title": "Iran war: What’s happening on day 58 as Tehran-Washington talks stall?",
      "velocityScore": 1.0,
      "category": "conflict",
      "countryName": "United States"
    },
    {
      "id": "rss_159f5d449229",
      "title": "Ghost MOTs: drivers warned over fake certificates that lead to huge repair bills",
      "velocityScore": 1.0,
      "category": "conflict",
      "countryName": "United Kingdom"
    },
    {
      "id": "rss_a6cbd2c62141",
      "title": "From syringes to stents: Iran war exposes NHS dependency on petrochemicals",
      "velocityScore": 1.0,
      "category": "conflict",
      "countryName": "Iran"
    },
    {
      "id": "rss_851353a670e3",
      "title": "Several killed in Colombia highway bomb attack ahead of presidential election",
      "velocityScore": 1.0,
      "category": "conflict",
      "countryName": "Colombia"
    },
    {
      "id": "rss_a31cde6caa59",
      "title": "Middle East war live: Iran's FM to return to Pakistan for talks as US envoys cancel visit",
      "velocityScore": 1.0,
      "category": "conflict",
      "countryName": "Pakistan"
    },
    {
      "id": "rss_7a93bcd947a4",
      "title": "Washington shooting: Is Trump safe? What we know so far",
      "velocityScore": 1.0,
      "category": "politics",
      "countryName": "United States"
    },
    {
      "id": "rss_1b9d9cf4b937",
      "title": "Injured Salah has played his last game for Liverpool: Egypt team official",
      "velocityScore": 1.0,
      "category": "politics",
      "countryName": "Egypt"
    },
    {
      "id": "rss_4dc32941f6e5",
      "title": "Donald Trump says being president is a 'dangerous profession' after shooting incident – video",
      "velocityScore": 1.0,
      "category": "politics",
      "countryName": "United States"
    }
  ],
  "risingRegions": [],
  "categoryTrends": {
    "politics": {
      "count": 1325,
      "change": "+1325",
      "changePercent": 100
    },
    "conflict": {
      "count": 370,
      "change": "+370",
      "changePercent": 100
    },
    "disaster": {
      "count": 160,
      "change": "+160",
      "changePercent": 100
    },
    "sports": {
      "count": 90,
      "change": "+90",
      "changePercent": 100
    },
    "health": {
      "count": 68,
      "change": "+68",
      "changePercent": 100
    },
    "economy": {
      "count": 47,
      "change": "+47",
      "changePercent": 100
    },
    "technology": {
      "count": 29,
      "change": "+29",
      "changePercent": 100
    },
    "science": {
      "count": 19,
      "change": "+19",
      "changePercent": 100
    }
  },
  "totalEvents": 2108,
  "totalSources": 2108,
  "globalStats": {
    "avgAttentionScore": 0.884,
    "totalArticles": 2108,
    "bubbleCount": 1911
  }
}