{
  "generatedAt": "2026-05-01T10:42:57.392464+00:00",
  "timeRange": "24h",
  "risingEvents": [
    {
      "id": "rss_2bdcbd6ad2aa",
      "title": "Who profits big from the war on Iran?",
      "velocityScore": 1.0,
      "category": "conflict",
      "countryName": "Iran"
    },
    {
      "id": "rss_a4eba3ba65c0",
      "title": "Oil prices rise again with little sign of war on Iran ending",
      "velocityScore": 1.0,
      "category": "conflict",
      "countryName": "Iran"
    },
    {
      "id": "rss_a0cb054c3bcb",
      "title": "More than 40 Iranian seafarers killed during US-Israeli war: Union leader",
      "velocityScore": 1.0,
      "category": "conflict",
      "countryName": "Iran"
    },
    {
      "id": "rss_64d73e6a3a04",
      "title": "Pakistan acting as backchannel as US and Iran inch towards deal, experts say",
      "velocityScore": 1.0,
      "category": "conflict",
      "countryName": "Pakistan"
    },
    {
      "id": "rss_d2ba784b0a64",
      "title": "NatWest faces £140m hit from Iran war as UK growth slows and inflation rises",
      "velocityScore": 1.0,
      "category": "conflict",
      "countryName": "United Kingdom"
    },
    {
      "id": "rss_4c69c4817041",
      "title": "Trump threatens to withdraw US troops from Italy and Spain – Europe live",
      "velocityScore": 1.0,
      "category": "conflict",
      "countryName": "United States"
    },
    {
      "id": "rss_c8422a18909d",
      "title": "Is Iran's hybrid warfare behind anti-Semitic attacks in Europe?",
      "velocityScore": 1.0,
      "category": "conflict",
      "countryName": "United States"
    },
    {
      "id": "rss_a8da31d6b700",
      "title": "US official says Iran war truce 'terminated' hostilities for war powers deadline",
      "velocityScore": 1.0,
      "category": "conflict",
      "countryName": "United States"
    }
  ],
  "risingRegions": [],
  "categoryTrends": {
    "politics": {
      "count": 1473,
      "change": "+1473",
      "changePercent": 100
    },
    "conflict": {
      "count": 353,
      "change": "+353",
      "changePercent": 100
    },
    "disaster": {
      "count": 127,
      "change": "+127",
      "changePercent": 100
    },
    "sports": {
      "count": 96,
      "change": "+96",
      "changePercent": 100
    },
    "health": {
      "count": 74,
      "change": "+74",
      "changePercent": 100
    },
    "economy": {
      "count": 41,
      "change": "+41",
      "changePercent": 100
    },
    "technology": {
      "count": 33,
      "change": "+33",
      "changePercent": 100
    },
    "science": {
      "count": 16,
      "change": "+16",
      "changePercent": 100
    }
  },
  "totalEvents": 2213,
  "totalSources": 2213,
  "globalStats": {
    "avgAttentionScore": 0.884,
    "totalArticles": 2213,
    "bubbleCount": 1985
  }
}