{
  "generatedAt": "2026-04-20T09:00:58.795850+00:00",
  "timeRange": "24h",
  "risingEvents": [
    {
      "id": "rss_171867343659",
      "title": "Iran war: What is happening on day 52 of the US-Israeli conflict?",
      "velocityScore": 1.0,
      "category": "conflict",
      "countryName": "Pakistan"
    },
    {
      "id": "rss_6158a1e618cb",
      "title": "US military releases video of marines seizing Iranian ship",
      "velocityScore": 1.0,
      "category": "conflict",
      "countryName": "Iran"
    },
    {
      "id": "rss_de17832fa709",
      "title": "Rebel Wilson accused in court of trying to paint actor as ‘money grabbing opportunist’ as defamation trial begins",
      "velocityScore": 1.0,
      "category": "conflict",
      "countryName": "Australia"
    },
    {
      "id": "rss_4d406fe9d78d",
      "title": "Woman who won legal case over greenhouse emissions awarded top environmental prize",
      "velocityScore": 1.0,
      "category": "conflict",
      "countryName": "United Kingdom"
    },
    {
      "id": "rss_51c0056a5031",
      "title": "Ukraine's fast-growing defense tech sector takes center stage in Iran war",
      "velocityScore": 1.0,
      "category": "conflict",
      "countryName": "Ukraine"
    },
    {
      "id": "rss_dc5aa416b17f",
      "title": "Strong 7.5 earthquake hits off Japan, tsunami warning issued",
      "velocityScore": 1.0,
      "category": "conflict",
      "countryName": "Japan"
    },
    {
      "id": "rss_c3becf4ff2b1",
      "title": "The Strokes highlight destroyed Gaza and Iran universities at Coachella",
      "velocityScore": 1.0,
      "category": "politics",
      "countryName": "Israel"
    },
    {
      "id": "rss_9b32e7cba8f7",
      "title": "Iran says no talks with US for now, casting doubt over Pakistan efforts",
      "velocityScore": 1.0,
      "category": "politics",
      "countryName": "Pakistan"
    }
  ],
  "risingRegions": [],
  "categoryTrends": {
    "politics": {
      "count": 1408,
      "change": "+1408",
      "changePercent": 100
    },
    "conflict": {
      "count": 408,
      "change": "+408",
      "changePercent": 100
    },
    "disaster": {
      "count": 148,
      "change": "+148",
      "changePercent": 100
    },
    "sports": {
      "count": 88,
      "change": "+88",
      "changePercent": 100
    },
    "economy": {
      "count": 57,
      "change": "+57",
      "changePercent": 100
    },
    "health": {
      "count": 46,
      "change": "+46",
      "changePercent": 100
    },
    "technology": {
      "count": 22,
      "change": "+22",
      "changePercent": 100
    },
    "science": {
      "count": 12,
      "change": "+12",
      "changePercent": 100
    }
  },
  "totalEvents": 2189,
  "totalSources": 2189,
  "globalStats": {
    "avgAttentionScore": 0.887,
    "totalArticles": 2189,
    "bubbleCount": 2007
  }
}